<?xml version="1.0" encoding="UTF-8"?>
<!DOCTYPE score-partwise PUBLIC "-//Recordare//DTD MusicXML 2.0 Partwise//EN" "http://www.musicxml.org/dtds/partwise.dtd">
<!-- INFO key="COM" value="Luise Adolpha Le Beau" -->
<!-- INFO key="CNT" value="Deutsch" -->
<!-- INFO key="TXO" value="Deutsch" -->
<!-- INFO key="OTL" value="Fru2hlingsnacht" -->
<!-- INFO key="LYR" value="Bernstein" -->
<!-- INFO key="OPR" value="Fu2nf Lieder" -->
<!-- INFO key="OPS" value="Op. 18" -->
<!-- INFO key="ONM" value="No. 5" -->
<!-- INFO key="ENC" value="Ben Fuhrman" -->
<!-- INFO key="YOR" value="Frauen komponieren: 25 Lieder fu2r Singstimme und Klavier" -->
<!-- INFO key="YOR" value="Mainz, B. Schott's So2hne, 1992." -->
<!-- INFO key="ODT" value="1879" -->
<!-- GCOMMENT value="NB: Only vocal melody encoded." -->
<!-- GCOMMENT value="NB: First instance of melodic material only encoded." -->
<!-- GCOMMENT value="created: 2/15/10 1:37PM" -->
<!-- GCOMMENT value="proofed and posted: 2/15/10 1:38PM" -->
<score-partwise version="2.0">
	<part-list>
		<score-part id="P1">
			<part-name></part-name>
		</score-part>
	</part-list>

	<part id="P1">
		<measure number="1">
			<attributes>
				<divisions>6</divisions>
			</attributes>
			<attributes>
				<key>
					<fifths>-4</fifths>
				</key>
			</attributes>
			<attributes>
				<time>
					<beats>4</beats>
					<beat-type>4</beat-type>
				</time>
			</attributes>
			<note>
				<rest/>
				<duration>12</duration>
				<voice>1</voice>
				<type>half</type>
			</note>
			<note>
				<rest/>
				<duration>6</duration>
				<voice>1</voice>
				<type>quarter</type>
			</note>
			<note>
				<pitch>
					<step>C</step>
					<octave>5</octave>
				</pitch>
				<duration>6</duration>
				<voice>1</voice>
				<type>quarter</type>
				<lyric number="1" name="verse">
					<syllabic>single</syllabic>
					<text>{Die</text>
				</lyric>
			</note>
		</measure>
		<measure number="2">
			<note>
				<pitch>
					<step>E</step>
					<alter>-1</alter>
					<octave>5</octave>
				</pitch>
				<duration>9</duration>
				<voice>1</voice>
				<type>quarter</type>
				<dot/>
				<lyric number="1" name="verse">
					<syllabic>single</syllabic>
					<text>Welt</text>
				</lyric>
			</note>
			<note>
				<pitch>
					<step>C</step>
					<octave>5</octave>
				</pitch>
				<duration>3</duration>
				<voice>1</voice>
				<type>eighth</type>
				<lyric number="1" name="verse">
					<syllabic>single</syllabic>
					<text>ist</text>
				</lyric>
			</note>
			<note>
				<pitch>
					<step>A</step>
					<alter>-1</alter>
					<octave>4</octave>
				</pitch>
				<duration>6</duration>
				<voice>1</voice>
				<type>quarter</type>
				<lyric number="1" name="verse">
					<syllabic>single</syllabic>
					<text>schla-</text>
				</lyric>
			</note>
			<note>
				<pitch>
					<step>B</step>
					<alter>-1</alter>
					<octave>4</octave>
				</pitch>
				<duration>6</duration>
				<voice>1</voice>
				<type>quarter</type>
				<lyric number="1" name="verse">
					<syllabic>single</syllabic>
					<text>-fen</text>
				</lyric>
			</note>
		</measure>
		<measure number="3">
			<note>
				<pitch>
					<step>E</step>
					<alter>-1</alter>
					<octave>4</octave>
				</pitch>
				<duration>12</duration>
				<voice>1</voice>
				<type>half</type>
				<lyric number="1" name="verse">
					<syllabic>single</syllabic>
					<text>gan</text>
				</lyric>
			</note>
			<note>
				<pitch>
					<step>A</step>
					<alter>-1</alter>
					<octave>4</octave>
				</pitch>
				<duration>6</duration>
				<voice>1</voice>
				<type>quarter</type>
				<lyric number="1" name="verse">
					<syllabic>single</syllabic>
					<text>-ge,</text>
				</lyric>
			</note>
			<note>
				<rest/>
				<duration>6</duration>
				<voice>1</voice>
				<type>quarter</type>
			</note>
		</measure>
		<measure number="4">
			<note>
				<pitch>
					<step>D</step>
					<alter>-1</alter>
					<octave>5</octave>
				</pitch>
				<duration>6</duration>
				<voice>1</voice>
				<type>quarter</type>
				<lyric number="1" name="verse">
					<syllabic>single</syllabic>
					<text>-still</text>
				</lyric>
			</note>
			<note>
				<pitch>
					<step>A</step>
					<alter>-1</alter>
					<octave>4</octave>
				</pitch>
				<duration>3</duration>
				<voice>1</voice>
				<type>eighth</type>
				<lyric number="1" name="verse">
					<syllabic>single</syllabic>
					<text>ist's</text>
				</lyric>
			</note>
			<note>
				<pitch>
					<step>A</step>
					<alter>-1</alter>
					<octave>4</octave>
				</pitch>
				<duration>3</duration>
				<voice>1</voice>
				<type>eighth</type>
				<lyric number="1" name="verse">
					<syllabic>single</syllabic>
					<text>in</text>
				</lyric>
			</note>
			<note>
				<pitch>
					<step>A</step>
					<alter>-1</alter>
					<octave>4</octave>
				</pitch>
				<duration>6</duration>
				<voice>1</voice>
				<type>quarter</type>
				<lyric number="1" name="verse">
					<syllabic>single</syllabic>
					<text>Busch</text>
				</lyric>
			</note>
			<note>
				<pitch>
					<step>B</step>
					<alter>-1</alter>
					<octave>4</octave>
				</pitch>
				<duration>6</duration>
				<voice>1</voice>
				<type>quarter</type>
				<lyric number="1" name="verse">
					<syllabic>single</syllabic>
					<text>und</text>
				</lyric>
			</note>
		</measure>
		<measure number="5">
			<note>
				<pitch>
					<step>C</step>
					<octave>5</octave>
				</pitch>
				<duration>12</duration>
				<voice>1</voice>
				<type>half</type>
				<lyric number="1" name="verse">
					<syllabic>single</syllabic>
					<text>Baum}</text>
				</lyric>
			</note>
			<note>
				<rest/>
				<duration>6</duration>
				<voice>1</voice>
				<type>quarter</type>
			</note>
			<note>
				<pitch>
					<step>C</step>
					<octave>5</octave>
				</pitch>
				<duration>6</duration>
				<voice>1</voice>
				<type>quarter</type>
				<lyric number="1" name="verse">
					<syllabic>single</syllabic>
					<text>{wo</text>
				</lyric>
			</note>
		</measure>
		<measure number="6">
			<note>
				<pitch>
					<step>D</step>
					<alter>-1</alter>
					<octave>5</octave>
				</pitch>
				<duration>9</duration>
				<voice>1</voice>
				<type>quarter</type>
				<dot/>
				<lyric number="1" name="verse">
					<syllabic>single</syllabic>
					<text>erst</text>
				</lyric>
			</note>
			<note>
				<pitch>
					<step>D</step>
					<alter>-1</alter>
					<octave>5</octave>
				</pitch>
				<duration>3</duration>
				<voice>1</voice>
				<type>eighth</type>
				<lyric number="1" name="verse">
					<syllabic>single</syllabic>
					<text>de</text>
				</lyric>
			</note>
			<note>
				<pitch>
					<step>E</step>
					<alter>-1</alter>
					<octave>5</octave>
				</pitch>
				<duration>6</duration>
				<voice>1</voice>
				<type>quarter</type>
				<lyric number="1" name="verse">
					<syllabic>single</syllabic>
					<text>Vo2g-</text>
				</lyric>
			</note>
			<note>
				<pitch>
					<step>F</step>
					<octave>5</octave>
				</pitch>
				<duration>6</duration>
				<voice>1</voice>
				<type>quarter</type>
				<lyric number="1" name="verse">
					<syllabic>single</syllabic>
					<text>-lein</text>
				</lyric>
			</note>
		</measure>
		<measure number="7">
			<note>
				<pitch>
					<step>E</step>
					<alter>-1</alter>
					<octave>5</octave>
				</pitch>
				<duration>12</duration>
				<voice>1</voice>
				<type>half</type>
				<lyric number="1" name="verse">
					<syllabic>single</syllabic>
					<text>san-</text>
				</lyric>
			</note>
			<note>
				<pitch>
					<step>C</step>
					<octave>5</octave>
				</pitch>
				<duration>6</duration>
				<voice>1</voice>
				<type>quarter</type>
				<lyric number="1" name="verse">
					<syllabic>single</syllabic>
					<text>-gen:</text>
				</lyric>
			</note>
			<note>
				<pitch>
					<step>A</step>
					<alter>-1</alter>
					<octave>4</octave>
				</pitch>
				<duration>3</duration>
				<voice>1</voice>
				<type>eighth</type>
				<lyric number="1" name="verse">
					<syllabic>single</syllabic>
					<text>gu-</text>
				</lyric>
			</note>
			<note>
				<pitch>
					<step>A</step>
					<alter>-1</alter>
					<octave>4</octave>
				</pitch>
				<duration>3</duration>
				<voice>1</voice>
				<type>eighth</type>
				<lyric number="1" name="verse">
					<syllabic>single</syllabic>
					<text>-te</text>
				</lyric>
			</note>
		</measure>
		<measure number="8">
			<note>
				<pitch>
					<step>C</step>
					<octave>5</octave>
				</pitch>
				<duration>9</duration>
				<voice>1</voice>
				<type>quarter</type>
				<dot/>
				<lyric number="1" name="verse">
					<syllabic>single</syllabic>
					<text>Nacht</text>
				</lyric>
			</note>
			<note>
				<pitch>
					<step>C</step>
					<octave>5</octave>
				</pitch>
				<duration>3</duration>
				<voice>1</voice>
				<type>eighth</type>
				<lyric number="1" name="verse">
					<syllabic>single</syllabic>
					<text>und</text>
				</lyric>
			</note>
			<note>
				<pitch>
					<step>B</step>
					<alter>-1</alter>
					<octave>4</octave>
				</pitch>
				<duration>6</duration>
				<voice>1</voice>
				<type>quarter</type>
				<lyric number="1" name="verse">
					<syllabic>single</syllabic>
					<text>su2-</text>
				</lyric>
			</note>
			<note>
				<pitch>
					<step>E</step>
					<alter>-1</alter>
					<octave>4</octave>
				</pitch>
				<duration>6</duration>
				<voice>1</voice>
				<type>quarter</type>
				<lyric number="1" name="verse">
					<syllabic>single</syllabic>
					<text>-ssen</text>
				</lyric>
			</note>
		</measure>
		<measure number="9">
			<note>
				<pitch>
					<step>A</step>
					<alter>-1</alter>
					<octave>4</octave>
				</pitch>
				<duration>12</duration>
				<voice>1</voice>
				<type>half</type>
				<lyric number="1" name="verse">
					<syllabic>single</syllabic>
					<text>Traum!}</text>
				</lyric>
			</note>
			<note>
				<rest/>
				<duration>6</duration>
				<voice>1</voice>
				<type>quarter</type>
			</note>
			<note>
				<pitch>
					<step>A</step>
					<alter>-1</alter>
					<octave>4</octave>
				</pitch>
				<duration>6</duration>
				<voice>1</voice>
				<type>quarter</type>
				<lyric number="1" name="verse">
					<syllabic>single</syllabic>
					<text>{Viel</text>
				</lyric>
			</note>
		</measure>
		<measure number="10">
			<note>
				<pitch>
					<step>G</step>
					<octave>4</octave>
				</pitch>
				<duration>6</duration>
				<voice>1</voice>
				<type>quarter</type>
				<lyric number="1" name="verse">
					<syllabic>single</syllabic>
					<text>tau-</text>
				</lyric>
			</note>
			<note>
				<pitch>
					<step>G</step>
					<octave>4</octave>
				</pitch>
				<duration>6</duration>
				<voice>1</voice>
				<type>quarter</type>
				<lyric number="1" name="verse">
					<syllabic>single</syllabic>
					<text>-send</text>
				</lyric>
			</note>
			<note>
				<pitch>
					<step>B</step>
					<alter>-1</alter>
					<octave>4</octave>
				</pitch>
				<duration>6</duration>
				<voice>1</voice>
				<type>quarter</type>
				<lyric number="1" name="verse">
					<syllabic>single</syllabic>
					<text>gol</text>
				</lyric>
			</note>
			<note>
				<pitch>
					<step>B</step>
					<alter>-1</alter>
					<octave>4</octave>
				</pitch>
				<duration>3</duration>
				<voice>1</voice>
				<type>eighth</type>
				<lyric number="1" name="verse">
					<syllabic>single</syllabic>
					<text>-de-</text>
				</lyric>
			</note>
			<note>
				<pitch>
					<step>B</step>
					<alter>-1</alter>
					<octave>4</octave>
				</pitch>
				<duration>3</duration>
				<voice>1</voice>
				<type>eighth</type>
				<lyric number="1" name="verse">
					<syllabic>single</syllabic>
					<text>-ne</text>
				</lyric>
			</note>
		</measure>
		<measure number="11">
			<note>
				<pitch>
					<step>E</step>
					<alter>-1</alter>
					<octave>5</octave>
				</pitch>
				<duration>12</duration>
				<voice>1</voice>
				<type>half</type>
				<lyric number="1" name="verse">
					<syllabic>single</syllabic>
					<text>Ster-</text>
				</lyric>
			</note>
			<note>
				<pitch>
					<step>B</step>
					<alter>-1</alter>
					<octave>4</octave>
				</pitch>
				<duration>12</duration>
				<voice>1</voice>
				<type>half</type>
				<lyric number="1" name="verse">
					<syllabic>single</syllabic>
					<text>-ne</text>
				</lyric>
			</note>
		</measure>
		<measure number="12">
			<note>
				<pitch>
					<step>A</step>
					<octave>4</octave>
				</pitch>
				<duration>6</duration>
				<voice>1</voice>
				<type>quarter</type>
				<accidental>natural</accidental>
				<lyric number="1" name="verse">
					<syllabic>single</syllabic>
					<text>strah-</text>
				</lyric>
			</note>
			<note>
				<pitch>
					<step>A</step>
					<octave>4</octave>
				</pitch>
				<duration>3</duration>
				<voice>1</voice>
				<type>eighth</type>
				<accidental>natural</accidental>
				<lyric number="1" name="verse">
					<syllabic>single</syllabic>
					<text>-len</text>
				</lyric>
			</note>
			<note>
				<pitch>
					<step>A</step>
					<octave>4</octave>
				</pitch>
				<duration>3</duration>
				<voice>1</voice>
				<type>eighth</type>
				<accidental>natural</accidental>
				<lyric number="1" name="verse">
					<syllabic>single</syllabic>
					<text>im</text>
				</lyric>
			</note>
			<note>
				<pitch>
					<step>B</step>
					<alter>-1</alter>
					<octave>4</octave>
				</pitch>
				<duration>6</duration>
				<voice>1</voice>
				<type>quarter</type>
				<lyric number="1" name="verse">
					<syllabic>single</syllabic>
					<text>e-</text>
				</lyric>
			</note>
			<note>
				<pitch>
					<step>C</step>
					<octave>5</octave>
				</pitch>
				<duration>3</duration>
				<voice>1</voice>
				<type>eighth</type>
				<lyric number="1" name="verse">
					<syllabic>single</syllabic>
					<text>-wi-</text>
				</lyric>
			</note>
			<note>
				<pitch>
					<step>C</step>
					<octave>5</octave>
				</pitch>
				<duration>3</duration>
				<voice>1</voice>
				<type>eighth</type>
				<lyric number="1" name="verse">
					<syllabic>single</syllabic>
					<text>-gen</text>
				</lyric>
			</note>
		</measure>
		<measure number="13">
			<note>
				<pitch>
					<step>B</step>
					<alter>-1</alter>
					<octave>4</octave>
				</pitch>
				<duration>12</duration>
				<voice>1</voice>
				<type>half</type>
				<lyric number="1" name="verse">
					<syllabic>single</syllabic>
					<text>Raum.}</text>
				</lyric>
			</note>
			<note>
				<rest/>
				<duration>6</duration>
				<voice>1</voice>
				<type>quarter</type>
			</note>
			<note>
				<pitch>
					<step>E</step>
					<alter>-1</alter>
					<octave>5</octave>
				</pitch>
				<duration>6</duration>
				<voice>1</voice>
				<type>quarter</type>
				<lyric number="1" name="verse">
					<syllabic>single</syllabic>
					<text>{Die</text>
				</lyric>
			</note>
		</measure>
		<measure number="14">
			<note>
				<pitch>
					<step>G</step>
					<octave>5</octave>
				</pitch>
				<duration>9</duration>
				<voice>1</voice>
				<type>quarter</type>
				<dot/>
				<lyric number="1" name="verse">
					<syllabic>single</syllabic>
					<text>gru2-</text>
				</lyric>
			</note>
			<note>
				<pitch>
					<step>F</step>
					<octave>5</octave>
				</pitch>
				<duration>3</duration>
				<voice>1</voice>
				<type>eighth</type>
				<lyric number="1" name="verse">
					<syllabic>single</syllabic>
					<text>-ssen</text>
				</lyric>
			</note>
			<note>
				<pitch>
					<step>E</step>
					<alter>-1</alter>
					<octave>4</octave>
				</pitch>
				<duration>6</duration>
				<voice>1</voice>
				<type>quarter</type>
				<lyric number="1" name="verse">
					<syllabic>single</syllabic>
					<text>aus</text>
				</lyric>
			</note>
			<note>
				<pitch>
					<step>C</step>
					<octave>5</octave>
				</pitch>
				<duration>6</duration>
				<voice>1</voice>
				<type>quarter</type>
				<lyric number="1" name="verse">
					<syllabic>single</syllabic>
					<text>der</text>
				</lyric>
			</note>
		</measure>
		<measure number="15">
			<note>
				<pitch>
					<step>E</step>
					<alter>-1</alter>
					<octave>5</octave>
				</pitch>
				<duration>12</duration>
				<voice>1</voice>
				<type>half</type>
				<lyric number="1" name="verse">
					<syllabic>single</syllabic>
					<text>Fer-</text>
				</lyric>
			</note>
			<note>
				<pitch>
					<step>B</step>
					<alter>-1</alter>
					<octave>4</octave>
				</pitch>
				<duration>3</duration>
				<voice>1</voice>
				<type>eighth</type>
				<lyric number="1" name="verse">
					<syllabic>single</syllabic>
					<text>-ne:</text>
				</lyric>
			</note>
			<note>
				<rest/>
				<duration>3</duration>
				<voice>1</voice>
				<type>eighth</type>
			</note>
			<note>
				<pitch>
					<step>G</step>
					<octave>4</octave>
				</pitch>
				<duration>3</duration>
				<voice>1</voice>
				<type>eighth</type>
				<lyric number="1" name="verse">
					<syllabic>single</syllabic>
					<text>gu-</text>
				</lyric>
			</note>
			<note>
				<pitch>
					<step>G</step>
					<octave>4</octave>
				</pitch>
				<duration>3</duration>
				<voice>1</voice>
				<type>eighth</type>
				<lyric number="1" name="verse">
					<syllabic>single</syllabic>
					<text>-te</text>
				</lyric>
			</note>
		</measure>
		<measure number="16">
			<note>
				<pitch>
					<step>C</step>
					<octave>5</octave>
				</pitch>
				<duration>9</duration>
				<voice>1</voice>
				<type>quarter</type>
				<dot/>
				<lyric number="1" name="verse">
					<syllabic>single</syllabic>
					<text>Nacht</text>
				</lyric>
			</note>
			<note>
				<pitch>
					<step>C</step>
					<octave>5</octave>
				</pitch>
				<duration>3</duration>
				<voice>1</voice>
				<type>eighth</type>
				<lyric number="1" name="verse">
					<syllabic>single</syllabic>
					<text>und</text>
				</lyric>
			</note>
			<note>
				<pitch>
					<step>B</step>
					<alter>-1</alter>
					<octave>4</octave>
				</pitch>
				<duration>6</duration>
				<voice>1</voice>
				<type>quarter</type>
				<lyric number="1" name="verse">
					<syllabic>single</syllabic>
					<text>su2-</text>
				</lyric>
			</note>
			<note>
				<pitch>
					<step>F</step>
					<octave>4</octave>
				</pitch>
				<duration>6</duration>
				<voice>1</voice>
				<type>quarter</type>
				<lyric number="1" name="verse">
					<syllabic>single</syllabic>
					<text>-ssen</text>
				</lyric>
			</note>
		</measure>
		<measure number="17">
			<note>
				<pitch>
					<step>G</step>
					<octave>4</octave>
				</pitch>
				<duration>12</duration>
				<voice>1</voice>
				<type>half</type>
				<lyric number="1" name="verse">
					<syllabic>single</syllabic>
					<text>Traum!}</text>
				</lyric>
			</note>
			<note>
				<rest/>
				<duration>6</duration>
				<voice>1</voice>
				<type>quarter</type>
			</note>
			<note>
				<pitch>
					<step>E</step>
					<alter>-1</alter>
					<octave>4</octave>
				</pitch>
				<duration>6</duration>
				<voice>1</voice>
				<type>quarter</type>
				<lyric number="1" name="verse">
					<syllabic>single</syllabic>
					<text>{Ruh</text>
				</lyric>
			</note>
		</measure>
		<measure number="18">
			<note>
				<pitch>
					<step>E</step>
					<alter>-1</alter>
					<octave>5</octave>
				</pitch>
				<duration>9</duration>
				<voice>1</voice>
				<type>quarter</type>
				<dot/>
				<lyric number="1" name="verse">
					<syllabic>single</syllabic>
					<text>aus</text>
				</lyric>
			</note>
			<note>
				<pitch>
					<step>C</step>
					<octave>5</octave>
				</pitch>
				<duration>3</duration>
				<voice>1</voice>
				<type>eighth</type>
				<lyric number="1" name="verse">
					<syllabic>single</syllabic>
					<text>von</text>
				</lyric>
			</note>
			<note>
				<pitch>
					<step>B</step>
					<alter>-1</alter>
					<octave>4</octave>
				</pitch>
				<duration>6</duration>
				<voice>1</voice>
				<type>quarter</type>
				<lyric number="1" name="verse">
					<syllabic>single</syllabic>
					<text>dei</text>
				</lyric>
			</note>
			<note>
				<pitch>
					<step>C</step>
					<octave>5</octave>
				</pitch>
				<duration>6</duration>
				<voice>1</voice>
				<type>quarter</type>
				<lyric number="1" name="verse">
					<syllabic>single</syllabic>
					<text>-nen</text>
				</lyric>
			</note>
		</measure>
		<measure number="19">
			<note>
				<pitch>
					<step>E</step>
					<alter>-1</alter>
					<octave>4</octave>
				</pitch>
				<duration>12</duration>
				<voice>1</voice>
				<type>half</type>
				<lyric number="1" name="verse">
					<syllabic>single</syllabic>
					<text>Mu2-</text>
				</lyric>
			</note>
			<note>
				<pitch>
					<step>A</step>
					<alter>-1</alter>
					<octave>4</octave>
				</pitch>
				<duration>6</duration>
				<voice>1</voice>
				<type>quarter</type>
				<lyric number="1" name="verse">
					<syllabic>single</syllabic>
					<text>-hen!</text>
				</lyric>
			</note>
			<note>
				<pitch>
					<step>A</step>
					<alter>-1</alter>
					<octave>4</octave>
				</pitch>
				<duration>6</duration>
				<voice>1</voice>
				<type>quarter</type>
				<lyric number="1" name="verse">
					<syllabic>single</syllabic>
					<text>Du</text>
				</lyric>
			</note>
		</measure>
		<measure number="20">
			<note>
				<pitch>
					<step>D</step>
					<alter>-1</alter>
					<octave>5</octave>
				</pitch>
				<duration>9</duration>
				<voice>1</voice>
				<type>quarter</type>
				<dot/>
				<lyric number="1" name="verse">
					<syllabic>single</syllabic>
					<text>schla2fst</text>
				</lyric>
			</note>
			<note>
				<pitch>
					<step>A</step>
					<alter>-1</alter>
					<octave>4</octave>
				</pitch>
				<duration>3</duration>
				<voice>1</voice>
				<type>eighth</type>
				<lyric number="1" name="verse">
					<syllabic>single</syllabic>
					<text>und</text>
				</lyric>
			</note>
			<note>
				<pitch>
					<step>A</step>
					<alter>-1</alter>
					<octave>4</octave>
				</pitch>
				<duration>6</duration>
				<voice>1</voice>
				<type>quarter</type>
				<lyric number="1" name="verse">
					<syllabic>single</syllabic>
					<text>ahnst</text>
				</lyric>
			</note>
			<note>
				<pitch>
					<step>B</step>
					<alter>-1</alter>
					<octave>4</octave>
				</pitch>
				<duration>6</duration>
				<voice>1</voice>
				<type>quarter</type>
				<lyric number="1" name="verse">
					<syllabic>single</syllabic>
					<text>es</text>
				</lyric>
			</note>
		</measure>
		<measure number="21">
			<note>
				<pitch>
					<step>C</step>
					<octave>5</octave>
				</pitch>
				<duration>12</duration>
				<voice>1</voice>
				<type>half</type>
				<lyric number="1" name="verse">
					<syllabic>single</syllabic>
					<text>kaum:}</text>
				</lyric>
			</note>
			<note>
				<rest/>
				<duration>12</duration>
				<voice>1</voice>
				<type>half</type>
			</note>
		</measure>
		<measure number="22">
			<note>
				<pitch>
					<step>F</step>
					<octave>5</octave>
				</pitch>
				<duration>6</duration>
				<voice>1</voice>
				<type>quarter</type>
				<lyric number="1" name="verse">
					<syllabic>single</syllabic>
					<text>{Mor-</text>
				</lyric>
			</note>
			<note>
				<pitch>
					<step>C</step>
					<octave>5</octave>
				</pitch>
				<duration>3</duration>
				<voice>1</voice>
				<type>eighth</type>
				<lyric number="1" name="verse">
					<syllabic>single</syllabic>
					<text>-gen</text>
				</lyric>
			</note>
			<note>
				<pitch>
					<step>B</step>
					<alter>-1</alter>
					<octave>4</octave>
				</pitch>
				<duration>3</duration>
				<voice>1</voice>
				<type>eighth</type>
				<lyric number="1" name="verse">
					<syllabic>single</syllabic>
					<text>wird's</text>
				</lyric>
			</note>
			<note>
				<pitch>
					<step>A</step>
					<alter>-1</alter>
					<octave>4</octave>
				</pitch>
				<duration>4</duration>
				<voice>1</voice>
				<type>quarter</type>
				<time-modification>
					<actual-notes>3</actual-notes>
					<normal-notes>2</normal-notes>
				</time-modification>
				<lyric number="1" name="verse">
					<syllabic>single</syllabic>
					<text>u2-</text>
				</lyric>
			</note>
			<note>
				<pitch>
					<step>G</step>
					<octave>4</octave>
				</pitch>
				<duration>4</duration>
				<voice>1</voice>
				<type>quarter</type>
				<time-modification>
					<actual-notes>3</actual-notes>
					<normal-notes>2</normal-notes>
				</time-modification>
				<lyric number="1" name="verse">
					<syllabic>single</syllabic>
					<text>-ber-</text>
				</lyric>
			</note>
			<note>
				<pitch>
					<step>A</step>
					<alter>-1</alter>
					<octave>4</octave>
				</pitch>
				<duration>4</duration>
				<voice>1</voice>
				<type>quarter</type>
				<time-modification>
					<actual-notes>3</actual-notes>
					<normal-notes>2</normal-notes>
				</time-modification>
				<lyric number="1" name="verse">
					<syllabic>single</syllabic>
					<text>-all</text>
				</lyric>
			</note>
		</measure>
		<measure number="23">
			<note>
				<pitch>
					<step>E</step>
					<alter>-1</alter>
					<octave>5</octave>
				</pitch>
				<duration>12</duration>
				<voice>1</voice>
				<type>half</type>
				<lyric number="1" name="verse">
					<syllabic>single</syllabic>
					<text>blu2-</text>
				</lyric>
			</note>
			<note>
				<pitch>
					<step>C</step>
					<octave>5</octave>
				</pitch>
				<duration>3</duration>
				<voice>1</voice>
				<type>eighth</type>
				<lyric number="1" name="verse">
					<syllabic>single</syllabic>
					<text>-hen!</text>
				</lyric>
			</note>
			<note>
				<rest/>
				<duration>3</duration>
				<voice>1</voice>
				<type>eighth</type>
			</note>
			<note>
				<pitch>
					<step>E</step>
					<alter>-1</alter>
					<octave>5</octave>
				</pitch>
				<duration>3</duration>
				<voice>1</voice>
				<type>eighth</type>
				<lyric number="1" name="verse">
					<syllabic>single</syllabic>
					<text>Gu-</text>
				</lyric>
			</note>
			<note>
				<pitch>
					<step>E</step>
					<alter>-1</alter>
					<octave>5</octave>
				</pitch>
				<duration>3</duration>
				<voice>1</voice>
				<type>eighth</type>
				<lyric number="1" name="verse">
					<syllabic>single</syllabic>
					<text>-te</text>
				</lyric>
			</note>
		</measure>
		<measure number="24">
			<note>
				<pitch>
					<step>A</step>
					<alter>-1</alter>
					<octave>5</octave>
				</pitch>
				<duration>9</duration>
				<voice>1</voice>
				<type>quarter</type>
				<dot/>
				<lyric number="1" name="verse">
					<syllabic>single</syllabic>
					<text>Nacht</text>
				</lyric>
			</note>
			<note>
				<pitch>
					<step>E</step>
					<alter>-1</alter>
					<octave>5</octave>
				</pitch>
				<duration>3</duration>
				<voice>1</voice>
				<type>eighth</type>
				<lyric number="1" name="verse">
					<syllabic>single</syllabic>
					<text>und</text>
				</lyric>
			</note>
			<note>
				<pitch>
					<step>C</step>
					<octave>5</octave>
				</pitch>
				<duration>6</duration>
				<voice>1</voice>
				<type>quarter</type>
				<lyric number="1" name="verse">
					<syllabic>single</syllabic>
					<text>su2-</text>
				</lyric>
			</note>
			<note>
				<pitch>
					<step>B</step>
					<alter>-1</alter>
					<octave>4</octave>
				</pitch>
				<duration>6</duration>
				<voice>1</voice>
				<type>quarter</type>
				<lyric number="1" name="verse">
					<syllabic>single</syllabic>
					<text>-ssen</text>
				</lyric>
			</note>
		</measure>
		<measure number="25">
			<note>
				<pitch>
					<step>E</step>
					<alter>-1</alter>
					<octave>5</octave>
				</pitch>
				<duration>12</duration>
				<voice>1</voice>
				<type>half</type>
				<lyric number="1" name="verse">
					<syllabic>single</syllabic>
					<text>Traum!}</text>
				</lyric>
			</note>
			<note>
				<rest/>
				<duration>6</duration>
				<voice>1</voice>
				<type>quarter</type>
			</note>
			<note>
				<pitch>
					<step>A</step>
					<alter>-1</alter>
					<octave>4</octave>
				</pitch>
				<duration>3</duration>
				<voice>1</voice>
				<type>eighth</type>
				<lyric number="1" name="verse">
					<syllabic>single</syllabic>
					<text>{Gu-</text>
				</lyric>
			</note>
			<note>
				<pitch>
					<step>A</step>
					<alter>-1</alter>
					<octave>4</octave>
				</pitch>
				<duration>3</duration>
				<voice>1</voice>
				<type>eighth</type>
				<lyric number="1" name="verse">
					<syllabic>single</syllabic>
					<text>-te</text>
				</lyric>
			</note>
		</measure>
		<measure number="26">
			<note>
				<pitch>
					<step>C</step>
					<octave>5</octave>
				</pitch>
				<duration>18</duration>
				<voice>1</voice>
				<type>half</type>
				<dot/>
				<lyric number="1" name="verse">
					<syllabic>single</syllabic>
					<text>Nacht</text>
				</lyric>
			</note>
			<note>
				<pitch>
					<step>C</step>
					<octave>5</octave>
				</pitch>
				<duration>6</duration>
				<voice>1</voice>
				<type>quarter</type>
				<lyric number="1" name="verse">
					<syllabic>single</syllabic>
					<text>und</text>
				</lyric>
			</note>
		</measure>
		<measure number="27">
			<note>
				<pitch>
					<step>B</step>
					<alter>-1</alter>
					<octave>4</octave>
				</pitch>
				<duration>12</duration>
				<voice>1</voice>
				<type>half</type>
				<lyric number="1" name="verse">
					<syllabic>single</syllabic>
					<text>su2-</text>
				</lyric>
			</note>
			<note>
				<pitch>
					<step>E</step>
					<alter>-1</alter>
					<octave>4</octave>
				</pitch>
				<duration>12</duration>
				<voice>1</voice>
				<type>half</type>
				<lyric number="1" name="verse">
					<syllabic>single</syllabic>
					<text>-ssen</text>
				</lyric>
			</note>
		</measure>
		<measure number="28">
			<note>
				<pitch>
					<step>A</step>
					<alter>-1</alter>
					<octave>4</octave>
				</pitch>
				<duration>18</duration>
				<voice>1</voice>
				<type>half</type>
				<dot/>
				<lyric number="1" name="verse">
					<syllabic>single</syllabic>
					<text>Traum!}</text>
				</lyric>
			</note>
			<note>
				<rest/>
				<duration>6</duration>
				<voice>1</voice>
				<type>quarter</type>
			</note>
		</measure>
	</part>
</score-partwise>
